listmakerkpanger88/__init__.py
listmakerkpanger88/list_maker.py
listmakerkpanger88-0.0.1.dist-info/LICENSE
listmakerkpanger88-0.0.1.dist-info/METADATA
listmakerkpanger88-0.0.1.dist-info/WHEEL
listmakerkpanger88-0.0.1.dist-info/top_level.txt
listmakerkpanger88-0.0.1.dist-info/RECORD
